{
    "name": "僵尸",
    "icon": "pvz:zombie_doll",
    "category": "pvz:intro",
    "pages": [
        {
            "type": "text",
            "text": "$(bpurple)僵尸$()是一种以脑子为食的疯狂生物，与$(bgreen)植物$()是死敌，同时还会$(l)攻击玩家和$(red)疯狂戴夫$()。僵尸有很多种类，有的在路上行走；有的可以开着造雪车；有的在海里潜水；甚至还有僵尸可以骑海豚。"
        },
        {
            "type": "text",
            "text": "击杀僵尸有很丰厚的奖励，玩家或其植物击杀僵尸可以获得$(bgreen)智慧树经验$()。同时僵尸死后有概率掉落$(borange)钱币（银币、金币）$()、$(bblue)宝石$()、$(borange)巧克力$()，以及植物种子、原始精华等等物品。如果这个僵尸被$(bgreen)绿光环绕$()，那么击杀它一定会掉落$(bgreen)能量豆$()。如果这个僵尸被$(byellow)金光环绕$()，那么击杀它一定会掉落$(byellow)阳光$()。"
        }
    ],
    "advancement": "pvz:adventure/root",
    "sortnum": 1
}